pynuit
