Metadata-Version: 2.1
Name: pyNUIT-NSAG
Version: 0.3.1
Summary: Wrapper for source term alaysis code NUIT
Home-page: https://github.com/thu-inet/pyNUIT
Author: THU-RSAG
Author-email: z-wj21@mails.tsinghua.edu.cn
License: UNKNOWN
Platform: UNKNOWN
Classifier: Development Status :: 3 - Alpha
Classifier: Programming Language :: Python :: 3
Classifier: License :: OSI Approved :: MIT License
Classifier: Operating System :: OS Independent
License-File: LICENCE
